nexusfm/__init__.py
nexusfm/cli.py
nexusfm/core.py
nexusfm/gui.py
nexusfm/terminal_commands.py
nexusfm-0.4.0.dist-info/METADATA
nexusfm-0.4.0.dist-info/WHEEL
nexusfm-0.4.0.dist-info/entry_points.txt
nexusfm-0.4.0.dist-info/top_level.txt
nexusfm-0.4.0.dist-info/RECORD
