Metadata-Version: 2.1
Name: nexusfm
Version: 0.4.0
Summary: An advanced personalized file manager with GUI and terminal interface
Home-page: https://github.com/jhasanlinix/nexusfm
Author: Jahid Hasan
Author-email: engjahidhasan20@gmail.com
Classifier: Programming Language :: Python :: 3
Classifier: License :: OSI Approved :: MIT License
Classifier: Operating System :: OS Independent
Requires-Python: >=3.6
Requires-Dist: PyQt5
